git_count/__init__.py
git_count/git_count.py
git_count-0.1.1.dist-info/LICENSE
git_count-0.1.1.dist-info/METADATA
git_count-0.1.1.dist-info/WHEEL
git_count-0.1.1.dist-info/entry_points.txt
git_count-0.1.1.dist-info/top_level.txt
git_count-0.1.1.dist-info/RECORD
